<mediawiki xmlns="http://www.mediawiki.org/xml/export-0.11/" xmlns:xsi="http://www.w3.org/2001/XMLSchema-instance" xsi:schemaLocation="http://www.mediawiki.org/xml/export-0.11/ http://www.mediawiki.org/xml/export-0.11.xsd" version="0.11" xml:lang="en">
<page>
  <title>Translations:Farming Setups/1/es</title>
  <ns>0</ns>
  <id>5481</id>
  <revision>
    <id>18253</id>
    <timestamp>2022-07-28T16:59:14Z</timestamp>
    <text space="preserve" bytes="102">[[File:Pokeclicker_Farm_Interface.png|400px|thumb|La granja, con múltiples bayas plantadas en ella.]]</text>
    <contributor>
      <username>Cthulhu Follower</username>
      <id>51</id>
    </contributor>
    <comment>Created page with "[[File:Pokeclicker_Farm_Interface.png|400px|thumb|La granja, con múltiples bayas plantadas en ella.]]"</comment>
    <model>wikitext</model>
    <parentid>0</parentid>
    <sha1>a123943b85a6048136bf80b724d830f5d5497e66</sha1>
  </revision>
</page></mediawiki>