<mediawiki xmlns="http://www.mediawiki.org/xml/export-0.11/" xmlns:xsi="http://www.w3.org/2001/XMLSchema-instance" xsi:schemaLocation="http://www.mediawiki.org/xml/export-0.11/ http://www.mediawiki.org/xml/export-0.11.xsd" version="0.11" xml:lang="en">
<page>
  <title>Translations:Shops/21/en</title>
  <ns>1198</ns>
  <id>10371</id>
  <revision>
    <id>30381</id>
    <timestamp>2022-12-05T14:20:18Z</timestamp>
    <text space="preserve" bytes="32">==[[Unova]]: Locations &amp; Items==</text>
    <contributor>
      <username>FuzzyBot</username>
      <id>133</id>
    </contributor>
    <comment>Importing a new version from external source</comment>
    <model>wikitext</model>
    <parentid>0</parentid>
    <sha1>4cccca295185a4310dbeb28f556e32690f7dc313</sha1>
  </revision>
</page></mediawiki>