<mediawiki xmlns="http://www.mediawiki.org/xml/export-0.11/" xmlns:xsi="http://www.w3.org/2001/XMLSchema-instance" xsi:schemaLocation="http://www.mediawiki.org/xml/export-0.11/ http://www.mediawiki.org/xml/export-0.11.xsd" version="0.11" xml:lang="en">
<page>
  <title>Translations:Cornn/3/fr</title>
  <ns>0</ns>
  <id>8697</id>
  <revision>
    <id>23967</id>
    <timestamp>2022-08-13T17:17:44Z</timestamp>
    <text space="preserve" bytes="492">== Tables de croissance ==
=== Stades de croissance ===
{| class="wikitable" | style = "image-rendering: pixelated"
! !! Pousse !! Arbuste !! Fleuri !! Mûr
|-
! Temps écoulé depuis plantation
| 18 mins 20 secs || 1 heure 6 mins 40 secs || 2 heures 13 mins 20 secs || 2 heures 30 mins - 5 heures
|-
! Animation
| &lt;center&gt; [[File:AllTreeSprout.png|50px]] || &lt;center&gt;[[File:CornnTreeTaller.png|50px]] || &lt;center&gt;[[File:CornnTreeBloom.png|50px]] || &lt;center&gt; [[File:CornnTreeBerry.png|50px]]
|}</text>
    <contributor>
      <username>LuK</username>
      <id>96</id>
    </contributor>
    <comment></comment>
    <model>wikitext</model>
    <parentid>23966</parentid>
    <sha1>816dd2a85f124c5d9d2eef4564334feffbd751f6</sha1>
  </revision>
</page></mediawiki>