<mediawiki xmlns="http://www.mediawiki.org/xml/export-0.11/" xmlns:xsi="http://www.w3.org/2001/XMLSchema-instance" xsi:schemaLocation="http://www.mediawiki.org/xml/export-0.11/ http://www.mediawiki.org/xml/export-0.11.xsd" version="0.11" xml:lang="en">
<page>
  <title>Translations:Pinap/5/fr</title>
  <ns>0</ns>
  <id>8176</id>
  <revision>
    <id>23024</id>
    <timestamp>2022-08-10T13:22:35Z</timestamp>
    <text space="preserve" bytes="69">== Organigramme ==
[[File:Nanana_-_Graph_découverte.png|200px]]
&lt;br&gt;</text>
    <contributor>
      <username>LuK</username>
      <id>96</id>
    </contributor>
    <comment>Created page with "== Organigramme == [[File:Nanana_-_Graph_découverte.png|200px]] &lt;br&gt;"</comment>
    <model>wikitext</model>
    <parentid>0</parentid>
    <sha1>e9c00762c5eda55ba3335ea492ea204876bf99ff</sha1>
  </revision>
</page></mediawiki>