<page>
  <title>Translations:Nanab/5/fr</title>
  <ns>0</ns>
  <id>8172</id>
  <revision>
    <id>23018</id>
    <timestamp>2022-08-10T12:16:10Z</timestamp>
    <text bytes="69" space="preserve">== Organigramme ==
[[File:Nanab_-_Graph_découverte.png |200px]]
&lt;br&gt;</text>
    <contributor>
      <username>LuK</username>
      <id>96</id>
    </contributor>
    <comment>Created page with "== Organigramme == [[File:Nanab_-_Graph_découverte.png |200px]] &lt;br&gt;"</comment>
    <model>wikitext</model>
    <parentid>0</parentid>
    <sha1>52f148120e1721bb17d4485f07c480256a463c85</sha1>
  </revision>
</page>