<page>
  <title>Translations:Wacan/2/en</title>
  <ns>0</ns>
  <id>6157</id>
  <revision>
    <id>18974</id>
    <timestamp>2022-07-29T08:01:44Z</timestamp>
    <text bytes="308" space="preserve">'''Wacan''' is a type of [[Berries|Berry]] that can be planted in the [[Farm]]. It can be obtained by surrounding an empty plot with at least 1 [[Iapapa]], at least 1 [[Qualot]], at least 1 [[Pinap]] and at least 1 [[Grepa]]. Various [[Farming Setups]] using Wacan can be found [[Farming Setups#Wacan|here]].</text>
    <contributor>
      <username>FuzzyBot</username>
      <id>133</id>
    </contributor>
    <comment>Importing a new version from external source</comment>
    <model>wikitext</model>
    <parentid>0</parentid>
    <sha1>463eab77d2c225054fccd06d50c539ccb26d7159</sha1>
  </revision>
</page>