<page>
  <title>Translations:Towns &amp; Cities/Page display title/en</title>
  <ns>0</ns>
  <id>6634</id>
  <revision>
    <id>19451</id>
    <timestamp>2022-07-29T08:04:01Z</timestamp>
    <text bytes="14" space="preserve">Towns &amp; Cities</text>
    <contributor>
      <username>FuzzyBot</username>
      <id>133</id>
    </contributor>
    <comment>Importing a new version from external source</comment>
    <model>wikitext</model>
    <parentid>0</parentid>
    <sha1>2e21268c264b7fdfa15df51a97f6e6f4aea5749f</sha1>
  </revision>
</page>