<page>
  <title>Translations:Masterball/2/fr</title>
  <ns>0</ns>
  <id>8562</id>
  <revision>
    <id>23685</id>
    <timestamp>2022-08-11T08:57:34Z</timestamp>
    <text bytes="15" space="preserve">==Description==</text>
    <contributor>
      <username>PetroleVB</username>
      <id>36</id>
    </contributor>
    <comment>Created page with "==Description=="</comment>
    <model>wikitext</model>
    <parentid>0</parentid>
    <sha1>e5fb55cd0d48613eee017266b93c836b7c3a17a7</sha1>
  </revision>
</page>