<page>
  <title>File:Yanma.png</title>
  <ns>6</ns>
  <id>1166</id>
  <revision>
    <id>28843</id>
    <timestamp>2022-12-04T13:35:25Z</timestamp>
    <text bytes="27" space="preserve">== Summary ==
Pokedex # 193</text>
    <contributor>
      <username>Maintenance script</username>
      <id>184</id>
    </contributor>
    <comment>Maintenance script uploaded [[File:Yanma.png]]</comment>
    <model>wikitext</model>
    <parentid>9613</parentid>
    <sha1>090523389e3a911dbeb3e39a14558f01ebc86cde</sha1>
  </revision>
</page>