<page>
  <title>Translations:NPCs/2/fr</title>
  <ns>0</ns>
  <id>7784</id>
  <revision>
    <id>22039</id>
    <timestamp>2022-08-06T09:18:57Z</timestamp>
    <text bytes="20" space="preserve">==PNjs par région==</text>
    <contributor>
      <username>PetroleVB</username>
      <id>36</id>
    </contributor>
    <comment>Created page with "==PNjs par région=="</comment>
    <model>wikitext</model>
    <parentid>0</parentid>
    <sha1>84cc28e1d2d79c4c90a5402c09fe2de5f18bffae</sha1>
  </revision>
</page>