<page>
  <title>Home Page</title>
  <ns>0</ns>
  <id>3</id>
  <revision>
    <id>102</id>
    <timestamp>2020-12-14T08:08:11Z</timestamp>
    <text bytes="4415" space="preserve">&lt;!--

--------------------------------------
 Welcome to the Main Page of the Pokéclicker Wiki!
--------------------------------------

When editing this page, please note a few things:


* The inexperienced may want to check out the "How to help" section on the "community portal" article linked on the sidebar.
* Remember this page is the most public face of the wiki - test edits are best done on a separate page.
* Sections within "&lt;! --" and "-- &gt;" markers (without the spaces) - like this entire section - are hidden comments, and can be separated by several lines. Be sure not to break them.


-------------------------------------------
The Main Page design code follows. Edit me!
-------------------------------------------



--&gt;

&lt;!------------ Title area --&gt;

&lt;div style="display:flex;"&gt;

&lt;!--Welcome--&gt;
&lt;div style="border:2px solid #00FFFF; background:#F2F2F2; padding:3px; -moz-border-radius:10px; margin: 0px 2px; text-align:center; flex-grow: 1;"&gt;
[[File:Welcome to the.png|link=Project:Community Portal|210px|Welcome]][[File:Blank.png|9px|link=]]&lt;br&gt;[[File:PokeClickerLogo.png|link=Project:About|300px|Pokéclicker Wiki]]&lt;br /&gt; [[File:Wiki_Custom.png|link=|80px]]&lt;br /&gt;
[[File:PC_E.png|80px|left|link=]][[File:PC_E.png|right|80px|link=]]
A community-driven wiki focusing on [[PokéClicker|Pokéclicker]] that [[Help:Editing|anyone can edit]].&lt;br /&gt;
&lt;span style="font-size:85%;"&gt;Today is {{CURRENTDAYNAME}} {{CURRENTMONTHNAME}} {{CURRENTDAY}}, {{CURRENTYEAR}} at {{CURRENTTIME}}.&lt;br /&gt;The wiki currently has [[Special:Statistics|'''{{NUMBEROFARTICLES}}''']] [[Special:Allpages|articles]] since May 31, 2008.&lt;br /&gt;There is a total of {{NUMBEROFACTIVEUSERS}} active users this month.&lt;/span&gt;&lt;br /&gt;
----
[[Wikia:Help:Tutorial|Wiki tutorial]]{{·}} [[:Category:Help|Help pages]]{{·}} [https://discord.gg/a6DFe4p Discord]{{·}} [[:Category:Content|Content]]{{·}} [[PokéClicker Wiki:Directory|Directory]]&lt;br /&gt;[[PokéClicker Wiki:Ruleset|Ruleset and guidelines]]{{·}} [[Special:SpecialPages|Special pages]]{{·}} [[Special:Categories|Categories]]{{·}} [[Special:Preferences|Preferences]]{{·}} [[Help:FAQ|FAQ]]
----
&lt;h2 style="font-size:120%; ; font-weight:normal"&gt; Pokéclicker is an open source game built around the story and content of the Pokémon games. This is a idle &amp; clicker type game which is currently in beta release phase with new content and patches getting released frequently.&lt;/h2&gt;
&lt;h2 style="font-size:120%; ; font-weight:normal"&gt;Pokémon is sole property of Nintendo and we do not claim to have any ownership of the same.&lt;/h2&gt;
----
You can start browsing this wiki by scrolling below and clicking on any of the links.

== '''Maps &amp; Navigation''' ==

{| class="wikitable" style="margin: auto;"
! [[Regions]] !! [[Farm]] !! [[Gyms]] !! [[Safari Zone]] !! [[Dungeons]]
|-
! [[Underground]] !! [[Shops]] !! [[NPCs]] !! colspan="2" style="border: 0px solid black;| [[Towns &amp; Cities]]
|}

== '''Items''' ==
{| class="wikitable" style="margin: auto;"
! [[Key Items]] !! [[Oak Items]] !! [[Pokéballs]] !! [[Battle Items]] !! [[Egg]]s
|-
![[Shops|Shop Items]] !! [[Farm Items]] !! [[Berries]] !! colspan="2" style="border: 0px solid black;| [[Underground#items|Underground Items]]
|}

== '''Currencies''' ==
{| class="wikitable" style="margin: auto;"
! [[Poke Dollar]] !! [[Dungeon Tokens]] !! [[Quest Points]]
|-
! [[Farming Points|Farm Points]] !! [[Diamonds]] !! [[Battle Points]]
|}

== '''Helpful Tools and Information''' ==
{| class="wikitable" style="margin: auto;"
! [[Shortcut Keys|Keyboard Shortcuts]] !! [https://discord.gg/a6DFe4p Discord] !! [[Shards]] !! [[Baby Pokémon|Baby Pokémon]] !! [[Speedruns]]
|-
! [[Route Statistics]] !! [[Shard-Type Advantages]] !! [[Events]] !! colspan="2" style="border: opx solid black;| [[List of Pokemons with attack|List of all Pokémon]]
|}
&lt;br&gt;

'''Didn't find the page you were looking for? try looking at this list of all [[Special:Statistics|'''{{NUMBEROFARTICLES}}''']] [[Special:AllPages|pages]]'''

This wiki is community managed but we do try to keep a [[To-Do list]] of what is missing or needs updating on this wiki. Please let us know on [https://discord.gg/a6DFe4p Discord] if you see anything that needs updating on a page or simply add it in the [[To-Do list]]. Thankyou.

&lt;/div&gt;

&lt;!--Contributors--&gt;
&lt;div id="contributors" style="float:right;"&gt;{{Contributors}}&lt;/div&gt;
&lt;/div&gt;

&lt;br clear="all" /&gt;

__NOTOC__ 
__NOEDITSECTION__</text>
    <contributor>
      <username>Claygame</username>
      <id>22</id>
    </contributor>
    <comment>made the table centered and added link to all pages</comment>
    <model>wikitext</model>
    <parentid>101</parentid>
    <sha1>b087ec6ff5471707342f10c26d36abc32d2e21eb</sha1>
  </revision>
</page>