<page>
  <title>Translations:Shops/14/fr</title>
  <ns>0</ns>
  <id>7821</id>
  <revision>
    <id>22136</id>
    <timestamp>2022-08-06T22:30:06Z</timestamp>
    <text bytes="921" space="preserve">{| class="wikitable"
|- 
| [[File:Boost_Mulch.png|30px]][[Farm Items/fr|Fertibérance]]&lt;br&gt; &amp;nbsp;{{Farmpoints}} 50 || [[File:Rich_Mulch.png|30px]][[Farm Items/fr|Fertibondance]]&lt;br&gt; &amp;nbsp;{{Farmpoints}} 100 || [[File:Surprise_Mulch.png|30px]][[Farm Items/fr|Fertistantané]]&lt;br&gt; &amp;nbsp;{{Farmpoints}} 150 || [[File:Amaze_Mulch.png|30px]][[Farm Items/fr|Fertiprodige]]&lt;br&gt; &amp;nbsp;{{Farmpoints}} 200
|-
| [[File:Freeze_Mulch.png|30px]][[Farm Items/fr|Fertibloque]]&lt;br&gt; &amp;nbsp;{{Farmpoints}} 350 || [[File:Berry_Shovel.png|30px]]&amp;thinsp;[[Farm Items/fr|Pel' à baie]]&lt;br&gt; &amp;nbsp;{{Farmpoints}} 300 || [[File:Mulch_Shovel.png|30px]]&amp;thinsp;[[Farm Items/fr|Pel' à engrais]]&lt;br&gt; &amp;nbsp;{{Farmpoints}} 300 || '''[[File:Sprinklotad.png|40px]][[Sprinklotad/fr|Nénurrosoir]]&lt;br&gt; &amp;nbsp;{{Farmpoints}} 10&amp;nbsp;000'''
|-
| [[File:Kerry.png|25px]] '''[[Farm Hands/fr|Assistant de ferme Kerry]]&lt;br&gt; &amp;nbsp;{{Farmpoints}} 100&amp;nbsp;000'''
|}</text>
    <contributor>
      <username>LeChatMG</username>
      <id>97</id>
    </contributor>
    <comment>Première traduction</comment>
    <model>wikitext</model>
    <parentid>0</parentid>
    <sha1>f2d0c67439a4d45aa809e5ed867e31278e8cf933</sha1>
  </revision>
</page>