<page>
  <title>Translations:Achievements/10/en</title>
  <ns>0</ns>
  <id>6771</id>
  <revision>
    <id>19588</id>
    <timestamp>2022-07-29T08:07:03Z</timestamp>
    <text bytes="415" space="preserve">===Captured===
{| class="wikitable"
! Name !! Description !! Bonus Percentage
|-
| First Team || Capture 100 Pokémon || +0.23%
|-
| Filling the PC || Capture 1,000 Pokémon || +0.45%
|-
| Pokémon Army || Capture 10,000 Pokémon || +0.68%
|-
| Pokémon Collector || Capture 100,000 Pokémon || +1.13%
|-
| You get a Pokémon, you get a Pokémon, everyone gets a Pokémon! || Capture 1,000,000 Pokémon || +2.26%
|}</text>
    <contributor>
      <username>FuzzyBot</username>
      <id>133</id>
    </contributor>
    <comment>Importing a new version from external source</comment>
    <model>wikitext</model>
    <parentid>0</parentid>
    <sha1>b8731a210451fe727c2b91c88a8a423da731dc59</sha1>
  </revision>
</page>