<page>
  <title>Wailmer Pail</title>
  <ns>0</ns>
  <id>135</id>
  <revision>
    <id>1602</id>
    <timestamp>2020-09-28T22:54:51Z</timestamp>
    <text bytes="331" space="preserve">== Details ==

===Description===
This is a tool for watering Berries you planted to make them grow more quickly

===Acquisition===
Completing Route 13 or Route 15, Whichever is done first

===Effects===
You can now access the farm on the corner of Route 14 and Route 15


{{Key Items}}&lt;br&gt;
[[Category:Key Items]] [[Category:Items]]</text>
    <contributor>
      <username>Liczale</username>
      <id>20</id>
    </contributor>
    <comment>/* Acquisition */</comment>
    <model>wikitext</model>
    <parentid>1601</parentid>
    <sha1>e9075bcdfb9309b2085ca82c8ed5ed89628057de</sha1>
  </revision>
  <revision>
    <id>1601</id>
    <timestamp>2020-09-28T22:54:41Z</timestamp>
    <text bytes="333" space="preserve">== Details ==

===Description===
This is a tool for watering Berries you planted to make them grow more quickly

===Acquisition===
Completing Route 13 or Route 15, (Whichever is done first)

===Effects===
You can now access the farm on the corner of Route 14 and Route 15


{{Key Items}}&lt;br&gt;
[[Category:Key Items]] [[Category:Items]]</text>
    <contributor>
      <username>Liczale</username>
      <id>20</id>
    </contributor>
    <comment>/* Acquisition */</comment>
    <model>wikitext</model>
    <parentid>1600</parentid>
    <sha1>7bc315669c5fb7af429cacec19602c2869704da2</sha1>
  </revision>
  <revision>
    <id>1600</id>
    <timestamp>2020-09-28T22:48:08Z</timestamp>
    <text bytes="294" space="preserve">== Details ==

===Description===
This is a tool for watering Berries you planted to make them grow more quickly

===Acquisition===
Completing Route 13

===Effects===
You can now access the farm on the corner of Route 14 and Route 15


{{Key Items}}&lt;br&gt;
[[Category:Key Items]] [[Category:Items]]</text>
    <contributor>
      <username>Liczale</username>
      <id>20</id>
    </contributor>
    <comment>/* Acquisition */</comment>
    <model>wikitext</model>
    <parentid>1599</parentid>
    <sha1>f02adf8056744f69782992d0706d85d37cb0ea36</sha1>
  </revision>
  <revision>
    <id>1599</id>
    <timestamp>2020-09-28T22:47:51Z</timestamp>
    <text bytes="331" space="preserve">== Details ==

===Description===
This is a tool for watering Berries you planted to make them grow more quickly

===Acquisition===
Completing Route 13 or Route 15 (Whichever you do first)

===Effects===
You can now access the farm on the corner of Route 14 and Route 15


{{Key Items}}&lt;br&gt;
[[Category:Key Items]] [[Category:Items]]</text>
    <contributor>
      <username>Liczale</username>
      <id>20</id>
    </contributor>
    <comment>/* Acquisition */</comment>
    <model>wikitext</model>
    <parentid>1598</parentid>
    <sha1>210a4823a57a862d59031844acce0e219871374d</sha1>
  </revision>
  <revision>
    <id>1598</id>
    <timestamp>2020-09-28T22:46:51Z</timestamp>
    <text bytes="294" space="preserve">== Details ==

===Description===
This is a tool for watering Berries you planted to make them grow more quickly

===Acquisition===
Completing Route 13

===Effects===
You can now access the farm on the corner of Route 14 and Route 15


{{Key Items}}&lt;br&gt;
[[Category:Key Items]] [[Category:Items]]</text>
    <contributor>
      <username>Liczale</username>
      <id>20</id>
    </contributor>
    <comment>Created page with "== Details ==  ===Description=== This is a tool for watering Berries you planted to make them grow more quickly  ===Acquisition=== Completing Route 13  ===Effects=== You can n..."</comment>
    <model>wikitext</model>
    <parentid>0</parentid>
    <sha1>f02adf8056744f69782992d0706d85d37cb0ea36</sha1>
  </revision>
</page>