<page>
  <title>User:Titubeur978</title>
  <ns>2</ns>
  <id>8935</id>
  <revision>
    <id>24405</id>
    <timestamp>2022-08-16T15:27:32Z</timestamp>
    <text bytes="186" space="preserve">Roses are red&lt;br&gt;
Violets are blue&lt;br&gt;
French fries aren't french&lt;br&gt;
c'est un triste fait&lt;br&gt;
et l'on ne peut rien y faire.&lt;br&gt;&lt;br&gt;&lt;br&gt;
ホウエン ホレヴア イン マイ ココロ</text>
    <contributor>
      <username>Titubeur978</username>
      <id>135</id>
    </contributor>
    <comment></comment>
    <model>wikitext</model>
    <parentid>24404</parentid>
    <sha1>0906cbe8d0ec3884ab40fef5b25d5445710916eb</sha1>
  </revision>
  <revision>
    <id>24404</id>
    <timestamp>2022-08-16T15:27:10Z</timestamp>
    <text bytes="155" space="preserve">Roses are red&lt;br&gt;
Violets are blue&lt;br&gt;
French fries aren't french&lt;br&gt;
c'est un triste fait&lt;br&gt;
et l'on ne peut rien y faire.&lt;br&gt;
Hoenn forever in my kokoro</text>
    <contributor>
      <username>Titubeur978</username>
      <id>135</id>
    </contributor>
    <comment></comment>
    <model>wikitext</model>
    <parentid>24403</parentid>
    <sha1>d6383cfc7383ff9df4ce0d09a66880f2f4533c67</sha1>
  </revision>
  <revision>
    <id>24403</id>
    <timestamp>2022-08-16T15:24:10Z</timestamp>
    <text bytes="132" space="preserve">Roses are red&lt;br&gt;
Violets are blue&lt;br&gt;
French fries aren't french&lt;br&gt;
c'est un triste fait&lt;br&gt;
et l'on ne peut rien y faire.&lt;br&gt;
M25</text>
    <contributor>
      <username>Titubeur978</username>
      <id>135</id>
    </contributor>
    <comment></comment>
    <model>wikitext</model>
    <parentid>24402</parentid>
    <sha1>f3a040c62dc80d188adf7a41264518d31d1b4526</sha1>
  </revision>
  <revision>
    <id>24402</id>
    <timestamp>2022-08-16T15:23:57Z</timestamp>
    <text bytes="128" space="preserve">Roses are red&lt;br&gt;
Violets are blue&lt;br&gt;
French fries aren't french&lt;br&gt;
c'est un triste fait&lt;br&gt;
et l'on ne peut rien y faire.
M25</text>
    <contributor>
      <username>Titubeur978</username>
      <id>135</id>
    </contributor>
    <comment></comment>
    <model>wikitext</model>
    <parentid>24401</parentid>
    <sha1>c43bd121914f5b305430831343ef2137e5ea82fd</sha1>
  </revision>
  <revision>
    <id>24401</id>
    <timestamp>2022-08-16T15:22:39Z</timestamp>
    <text bytes="124" space="preserve">Roses are red&lt;br&gt;
Violets are blue&lt;br&gt;
French fries aren't french&lt;br&gt;
c'est un triste fait&lt;br&gt;
et l'on ne peut rien y faire.</text>
    <contributor>
      <username>Titubeur978</username>
      <id>135</id>
    </contributor>
    <comment></comment>
    <model>wikitext</model>
    <parentid>24400</parentid>
    <sha1>7186c2662464e8934739b7fa77f9956bd826fba4</sha1>
  </revision>
  <revision>
    <id>24400</id>
    <timestamp>2022-08-16T15:18:24Z</timestamp>
    <text bytes="123" space="preserve">Roses are red&lt;br&gt;
Violets are blue&lt;br&gt;
French fries aren't french&lt;br&gt;
c'est un triste fait&lt;br&gt;
et l'on ne peut rien y faire</text>
    <contributor>
      <username>Titubeur978</username>
      <id>135</id>
    </contributor>
    <comment></comment>
    <model>wikitext</model>
    <parentid>24399</parentid>
    <sha1>eeda46d3aa7212af3ec5a59fdc4126d0af019093</sha1>
  </revision>
  <revision>
    <id>24399</id>
    <timestamp>2022-08-16T15:17:29Z</timestamp>
    <text bytes="124" space="preserve">Roses are red&lt;br&gt;
Violets are blue&lt;br&gt;
French fries aren't french&lt;br&gt;
c'est un triste fait&lt;br&gt;
et l'on ne peut rien y faire.</text>
    <contributor>
      <username>Titubeur978</username>
      <id>135</id>
    </contributor>
    <comment></comment>
    <model>wikitext</model>
    <parentid>24398</parentid>
    <sha1>7186c2662464e8934739b7fa77f9956bd826fba4</sha1>
  </revision>
  <revision>
    <id>24398</id>
    <timestamp>2022-08-16T15:17:19Z</timestamp>
    <text bytes="123" space="preserve">Roses are red&lt;br&gt;
Violets are blue&lt;br&gt;
French fries aren't french&lt;br&gt;
c'est un triste fait&lt;br&gt;
et l'on ne peut rien y faire</text>
    <contributor>
      <username>Titubeur978</username>
      <id>135</id>
    </contributor>
    <comment></comment>
    <model>wikitext</model>
    <parentid>24397</parentid>
    <sha1>eeda46d3aa7212af3ec5a59fdc4126d0af019093</sha1>
  </revision>
  <revision>
    <id>24397</id>
    <timestamp>2022-08-16T15:05:24Z</timestamp>
    <text bytes="127" space="preserve">Roses are red&lt;br&gt;
Violets are blue&lt;br&gt;
French fries aren't french&lt;br&gt;
c'est un triste fait&lt;br&gt;
et l'on ne peut rien y faire&lt;br&gt;</text>
    <contributor>
      <username>Titubeur978</username>
      <id>135</id>
    </contributor>
    <comment></comment>
    <model>wikitext</model>
    <parentid>24396</parentid>
    <sha1>a6c446027af38edd779b12a06295ee2820e630f8</sha1>
  </revision>
  <revision>
    <id>24396</id>
    <timestamp>2022-08-16T15:03:04Z</timestamp>
    <text bytes="107" space="preserve">Roses are red
Violets are blue
French fries aren't french
c'est un triste fait
et l'on ne peut rien y faire</text>
    <contributor>
      <username>Titubeur978</username>
      <id>135</id>
    </contributor>
    <comment>Created page with "Roses are red Violets are blue French fries aren't french c'est un triste fait et l'on ne peut rien y faire"</comment>
    <model>wikitext</model>
    <parentid>0</parentid>
    <sha1>bd419d5faa4c664e70ffd9056c4c2eca06f6a095</sha1>
  </revision>
</page>