<page>
  <title>Translations:Achievements/22/fr</title>
  <ns>0</ns>
  <id>7031</id>
  <revision>
    <id>20248</id>
    <timestamp>2022-07-29T14:02:04Z</timestamp>
    <text bytes="527" space="preserve">===Fermier===
{| class="wikitable"
! Nom !! Description !! % de bonus
|-
| Mon nouveau loisir salissant || Débloquer 3 parcelles dans la Ferme || +0,23%
|-
| Jardinier associé || Débloquer 9 parcelles dans la Ferme || +0,68%
|-
| Horticulture || Débloquer 25 parcelles dans la Ferme || +1,13%
|-
| Qui a planté ça ici ? || Débloquer 8 Baies|| +0,45%
|-
| Fermier en formation || Débloquer 18 Baies || +0,90%
|-
| Apprenti Fermier || Débloquer 36 Baies || +1,35%
|-
| Maître Fermier || Débloquer 67 Baies || +1,80%
|}</text>
    <contributor>
      <username>Razikd</username>
      <id>33</id>
    </contributor>
    <comment>Created page with "===Fermier=== {| class="wikitable" ! Nom !! Description !! % de bonus |- | Mon nouveau loisir salissant || Débloquer 3 parcelles dans la Ferme || +0,23% |- | Jardinier associé || Débloquer 9 parcelles dans la Ferme || +0,68% |- | Horticulture || Débloquer 25 parcelles dans la Ferme || +1,13% |- | Qui a planté ça ici ? || Débloquer 8 Baies|| +0,45% |- | Fermier en formation || Débloquer 18 Baies || +0,90% |- | Apprenti Fermier || Débloquer 36 Baies || +1,35% |- |..."</comment>
    <model>wikitext</model>
    <parentid>0</parentid>
    <sha1>f865649e17c03b143405af00fb563af9a620f68f</sha1>
  </revision>
</page>