<mediawiki xmlns="http://www.mediawiki.org/xml/export-0.11/" xmlns:xsi="http://www.w3.org/2001/XMLSchema-instance" xsi:schemaLocation="http://www.mediawiki.org/xml/export-0.11/ http://www.mediawiki.org/xml/export-0.11.xsd" version="0.11" xml:lang="en">
<page>
  <title>Mystery Egg (Key Item)</title>
  <ns>0</ns>
  <id>12127</id>
  <revision>
    <id>35057</id>
    <timestamp>2022-12-15T20:39:37Z</timestamp>
    <text space="preserve" bytes="840">{{Infobox Key Item
|name       = Mystery Egg
|image      = [[File:Mystery_Egg_Item.png]]
|caption    = Artwork of the ''Mystery Egg''.
|use        = Allows use of the [[Pokémon Day Care|Pokémon Day Care]]
|obtain     = Defeat 10 Pokémon on [[Kanto#Routes|Kanto Route 5]]
}}

===Description===
A mysterious Egg obtained from Mr. Pokémon. This allows you to use the [[Pokémon Day Care|Pokémon Day Care]] to help improve your Pokémon Attack. Some baby Pokémon can only be found through breeding, too!

===Acquisition===
Upon defeating 10 Pokémon in [[Kanto#Routes|Kanto Route 5]], Professor Oak will give the player the Mystery Egg allowing access to the [[Pokémon Day Care|Pokémon Day Care]].

===Effects===
Access to the [[Pokémon Day Care|Pokémon Day Care]]

&lt;br&gt;&lt;br&gt;
{{Key Items}}&lt;br&gt;
[[Category:Key Items]] [[Category:Items]]</text>
    <contributor>
      <username>ThePantMan</username>
      <id>8</id>
    </contributor>
    <comment>Text replacement - "(?&lt;!{{)(?&lt;!{{Route)Pokemon" to "Pokémon"</comment>
    <model>wikitext</model>
    <parentid>33140</parentid>
    <sha1>3f0d35236ca08bae63a65a9de886f1e4e39a3e5f</sha1>
  </revision>
</page></mediawiki>