<mediawiki xmlns="http://www.mediawiki.org/xml/export-0.11/" xmlns:xsi="http://www.w3.org/2001/XMLSchema-instance" xsi:schemaLocation="http://www.mediawiki.org/xml/export-0.11/ http://www.mediawiki.org/xml/export-0.11.xsd" version="0.11" xml:lang="en">
<page>
  <title>Translations:Pokémon Day Care/6/en</title>
  <ns>1198</ns>
  <id>11729</id>
  <revision>
    <id>32313</id>
    <timestamp>2022-12-07T12:28:40Z</timestamp>
    <text space="preserve" bytes="366">There are three different types of hatch-able resources in Pokéclicker: obtained Pokémon Eggs, Fossils, and already obtained level 100 Pokémon. Pokémon Eggs are typically purchased in Shops and Fossils are typically mined from the [[Underground]]. The Egg/Fossil/Obtained Pokémon that can be bred each have their own distinct tab in the Pokémon Day Care modal.</text>
    <contributor>
      <username>FuzzyBot</username>
      <id>133</id>
    </contributor>
    <comment>Importing a new version from external source</comment>
    <model>wikitext</model>
    <parentid>0</parentid>
    <sha1>66bd794be5e293b0531e10b8fb0bf42bab5f434f</sha1>
  </revision>
</page></mediawiki>