<mediawiki xmlns="http://www.mediawiki.org/xml/export-0.11/" xmlns:xsi="http://www.w3.org/2001/XMLSchema-instance" xsi:schemaLocation="http://www.mediawiki.org/xml/export-0.11/ http://www.mediawiki.org/xml/export-0.11.xsd" version="0.11" xml:lang="en">
<page>
  <title>Translations:Dowsing Machine/Page display title/en</title>
  <ns>1198</ns>
  <id>12607</id>
  <revision>
    <id>35250</id>
    <timestamp>2022-12-15T21:41:11Z</timestamp>
    <text space="preserve" bytes="15">Dowsing Machine</text>
    <contributor>
      <username>FuzzyBot</username>
      <id>133</id>
    </contributor>
    <comment>Importing a new version from external source</comment>
    <model>wikitext</model>
    <parentid>0</parentid>
    <sha1>2e110dacb6b4ad95106ab2b3047e2dbd5a37b029</sha1>
  </revision>
</page></mediawiki>