<mediawiki xmlns="http://www.mediawiki.org/xml/export-0.11/" xmlns:xsi="http://www.w3.org/2001/XMLSchema-instance" xsi:schemaLocation="http://www.mediawiki.org/xml/export-0.11/ http://www.mediawiki.org/xml/export-0.11.xsd" version="0.11" xml:lang="en">
<page>
  <title>Translations:Charti/1/fr</title>
  <ns>1198</ns>
  <id>11499</id>
  <revision>
    <id>31903</id>
    <timestamp>2022-12-06T10:11:38Z</timestamp>
    <text space="preserve" bytes="496">{{Infobox Berry
|name    = #48 Charti
|image   = [[File:Charti.png]]
|caption = Cette baie est souvent utilisée en pickle à cause de son goût très sec. Elle peut aussi être mangée crue et a un goût provocateur. Cette plante durcit la terre à ses alentours, ce qui diminue les chances de replante. 
|growtime  = 10h 30m 0s
|harvest = 32 baies
|replant = 5%
|mutation = 0,01%
|points = 2 000
|flavor = &lt;div style="clear:both;"&gt;&lt;/div&gt;
*10 Épicée
*20 Sèche
*0 Sucrée
*0 Amère
*0 Acide
}}</text>
    <contributor>
      <username>Razikd</username>
      <id>33</id>
    </contributor>
    <comment>Imported translation using [[Special:PageMigration|page migration]]</comment>
    <model>wikitext</model>
    <parentid>0</parentid>
    <sha1>723f0784959801091b40fa27359bcc007f3976a4</sha1>
  </revision>
</page></mediawiki>